calcfunc/Func.py
calcfunc/__init__.py
calcfunc-2.0.0.dist-info/METADATA
calcfunc-2.0.0.dist-info/WHEEL
calcfunc-2.0.0.dist-info/license.txt
calcfunc-2.0.0.dist-info/top_level.txt
calcfunc-2.0.0.dist-info/RECORD
