Metadata-Version: 2.1
Name: calcfunc
Version: 2.0.0
Summary: simple calculate method
Home-page: http://git.mom.comac.int
Author: Way Yan
Author-email: UNKNOWN
License: MIT
Platform: UNKNOWN
